LICENSE.txt
MANIFEST.in
README.rst
setup.cfg
setup.py
faodata/__init__.py
faodata/faodownload.py
faodata/faomap.py
faodata/ne_110m_admin_0_countries.README.html
faodata/ne_110m_admin_0_countries.VERSION.txt
faodata/ne_110m_admin_0_countries.dbf
faodata/ne_110m_admin_0_countries.prj
faodata/ne_110m_admin_0_countries.shp
faodata/ne_110m_admin_0_countries.shx
faodata.egg-info/PKG-INFO
faodata.egg-info/SOURCES.txt
faodata.egg-info/dependency_links.txt
faodata.egg-info/requires.txt
faodata.egg-info/top_level.txt