Metadata-Version: 1.1
Name: faodata
Version: 1.1
Summary: Download data from the Food and Agriculture Organisation (FAO)
Home-page: https://bitbucket.org/jlerat/faodata
Author: Julien Lerat
Author-email: julien.lerat@gmail.com
License: MIT
Download-URL: https://bitbucket.org/jlerat/faodata/downloads
Keywords: FAO,Web Service,GIS
Platform: UNKNOWN
Classifier: Operating System :: OS Independent
Classifier: Development Status :: 4 - Beta
Classifier: Programming Language :: Python :: 2.6
Classifier: License :: OSI Approved :: MIT License
